Metadata-Version: 2.1
Name: nbc
Version: 1.1.3
Summary: Number Base Converter
Home-page: https://gitlab.com/v01d-gl/number-base-converter
Author: v01d
Author-email: v01dmain@aol.com
License: Apache 2.0
Platform: UNKNOWN
